tablespy/__init__.py
tablespy/inspection.py
tablespy/inspector.py
tablespy/printer.py
tablespy/scripts/__init__.py
tablespy/scripts/tablespy.py
tablespy-0.0.4.dist-info/LICENSE.md
tablespy-0.0.4.dist-info/METADATA
tablespy-0.0.4.dist-info/WHEEL
tablespy-0.0.4.dist-info/entry_points.txt
tablespy-0.0.4.dist-info/top_level.txt
tablespy-0.0.4.dist-info/RECORD
