Metadata-Version: 2.1
Name: tablespy
Version: 0.0.4
Summary: Table spotter for spreadsheets
Home-page: https://github.com/flaxandteal/tablespy
Author: Phil Weir
Author-email: phil.weir@flaxandteal.co.uk
License: MIT
Keywords: pandas table ods xls
Platform: UNKNOWN
Classifier: Development Status :: 3 - Alpha
Classifier: Intended Audience :: Developers
Classifier: License :: OSI Approved :: MIT License
Classifier: Programming Language :: Python :: 3.7
Requires-Dist: Click
Requires-Dist: pandas
Requires-Dist: scikit-image
Requires-Dist: tabulator[ods]
